bloark/__init__.py
bloark/builder.py
bloark/builder_helpers.py
bloark/decorators.py
bloark/logger.py
bloark/logger_init.py
bloark/modifier.py
bloark/reader.py
bloark/utils.py
bloark/warehouse.py
bloark-2.3.3.dist-info/LICENSE
bloark-2.3.3.dist-info/METADATA
bloark-2.3.3.dist-info/WHEEL
bloark-2.3.3.dist-info/entry_points.txt
bloark-2.3.3.dist-info/RECORD
