Metadata-Version: 2.1
Name: bloark
Version: 2.3.3
Summary: Blocks Architecture (BloArk): A unified tool for processing revision-based data efficiently.
Home-page: https://bloark.lingxi.li/
License: GNU GPL
Author: Lingxi Li
Author-email: hi@lingxi.li
Requires-Python: >=3.8,<4
Classifier: License :: Other/Proprietary License
Classifier: Programming Language :: Python :: 3
Classifier: Programming Language :: Python :: 3.8
Classifier: Programming Language :: Python :: 3.9
Classifier: Programming Language :: Python :: 3.10
Classifier: Programming Language :: Python :: 3.11
Classifier: Programming Language :: Python :: 3.12
Requires-Dist: beautifulsoup4 (>=4.12.2,<5.0.0)
Requires-Dist: jsonlines (>=3.1.0,<4.0.0)
Requires-Dist: psutil (>=5.9.5,<6.0.0)
Requires-Dist: py7zr (>=0.20.5,<0.21.0)
Requires-Dist: requests (>=2.31.0,<3.0.0)
Requires-Dist: tqdm (>=4.65.0,<5.0.0)
Requires-Dist: wrapt (>=1.15.0,<2.0.0)
Requires-Dist: xmltodict (>=0.13.0,<0.14.0)
Requires-Dist: zstandard (>=0.21.0,<0.22.0)
Project-URL: Repository, https://github.com/lilingxi01/bloark
